parsomics_plugin_clean/__init__.py
parsomics_plugin_clean/file_factory.py
parsomics_plugin_clean/parser.py
parsomics_plugin_clean/plugin_initializer.py
parsomics_plugin_clean/populate.py
parsomics_plugin_clean/processor.py
parsomics_plugin_clean/validated_file.py
parsomics_plugin_clean-0.1.3.dist-info/LICENSE
parsomics_plugin_clean-0.1.3.dist-info/METADATA
parsomics_plugin_clean-0.1.3.dist-info/WHEEL
parsomics_plugin_clean-0.1.3.dist-info/RECORD
