Metadata-Version: 2.3
Name: parsomics-plugin-clean
Version: 0.1.3
Summary: A parsomics plugin to populate protein annotations with CLEAN
License: GPL-3.0
Author: RafaelaLuz
Author-email: rafaela24021@ilum.cnpem.br
Requires-Python: >=3.12,<4.0
Classifier: License :: OSI Approved :: GNU General Public License v3 (GPLv3)
Classifier: Programming Language :: Python :: 3
Classifier: Programming Language :: Python :: 3.12
Classifier: Programming Language :: Python :: 3.13
Requires-Dist: parsomics-core (>=4.1.0,<5.0.0)
Requires-Dist: polars (>=1.22.0,<2.0.0)
Requires-Dist: pydantic (>=2.10.6,<3.0.0)
Requires-Dist: sqlalchemy (>=2.0.38,<3.0.0)
Requires-Dist: sqlmodel (>=0.0.22,<0.0.23)
